sorobn/__init__.py
sorobn/bayes_net.py
sorobn/examples.py
sorobn/gui.py
sorobn/structure.py
sorobn/test_bayes_net.py
sorobn-0.3.1.dist-info/LICENSE
sorobn-0.3.1.dist-info/METADATA
sorobn-0.3.1.dist-info/WHEEL
sorobn-0.3.1.dist-info/entry_points.txt
sorobn-0.3.1.dist-info/RECORD
